proj/__init__.py
proj/configfile.py
proj/exceptions.py
proj/fs.py
proj/logic.py
proj/ui.py
proj-0.2.0.dist-info/AUTHORS.rst
proj-0.2.0.dist-info/LICENSE
proj-0.2.0.dist-info/METADATA
proj-0.2.0.dist-info/WHEEL
proj-0.2.0.dist-info/entry_points.txt
proj-0.2.0.dist-info/top_level.txt
proj-0.2.0.dist-info/RECORD
