Metadata-Version: 1.1
Name: proj
Version: 0.2.0
Summary: A command-line manager for archiving and retrieving projects.
Home-page: https://github.com/larsyencken/proj
Author: Lars Yencken
Author-email: lars@yencken.org
License: BSD
Keywords: proj
Platform: UNKNOWN
Classifier: Development Status :: 2 - Pre-Alpha
Classifier: Intended Audience :: Developers
Classifier: License :: OSI Approved :: BSD License
Classifier: Natural Language :: English
Classifier: Programming Language :: Python :: 3.7
Classifier: Programming Language :: Python :: 3.8
